{
    "car": [
        {
            "id": 0,
            "name": "上汽大众-途观",
            "color": ["白色","黑色","灰色","银色"],
            "category": "SUV",
            "seat": 4,
            "price": "170000-230000",
            "power": "1.5T,2.0T",
            "usage": "家用/商用"
        },
        {
            "id": 1,
            "name": "上汽大众-朗逸",
            "color": ["白色","黑色","银色"],
            "category": "轿车",
            "seat": 4,
            "price": "120000-150000",
            "power": "1.5T,2.0T",
            "usage": "家用"
        },
        {
            "id": 2,
            "name": "上汽大众-捷达",
            "color": ["白色","黑色","灰色"],
            "category": "轿车",
            "seat": 4,
            "price": "100000-130000",
            "power": "1.5L,2.0L",
            "usage": "家用"
        },
        {
            "id": 3,
            "name": "上汽大众-桑塔纳",
            "color": ["白色","黑色"],
            "category": "轿车",
            "seat": 4,
            "price": "80000-100000",
            "power": "1.6L,1.8L",
            "usage": "家用/商用"
        },
        {
            "id": 4,
            "name": "上汽大众-途昂",
            "color": ["白色","黑色","灰色","银色"],
            "category": "SUV",
            "seat": 7,
            "price": "200000-230000",
            "power": "1.5T,2.0T",
            "usage": "商用/越野"
        },
        {
            "id": 5,
            "name": "上汽大众-帕萨特",
            "color": ["白色","黑色","灰色","银色"],
            "category": "轿车",
            "seat": 4,
            "price": "210000-240000",
            "power": "1.8T,2.0T",
            "usage": "家用/商用"
        },
        {
            "id": 6,
            "name": "上汽大众-凌度",
            "color": ["白色","黑色","灰色","红色"],
            "category": "轿车",
            "seat": 4,
            "price": "120000-150000",
            "power": "1.5L,2.0L",
            "usage": "家用"
        }
    ]
}
